{
    "Changes": [
        {
            "Action": "EditData",
            "Target": "Data/TriggerActions",
            "Entries": {
                //todo - добавить событие для свидания у фонтана
                // "{{ModId}}_triggerHarveyNoteGirlfriend": {
                //   "Id": "{{ModId}}_triggerHarveyNoteGirlfriend",
                //   "Trigger": "DayStarted",
                //   "Condition": "DAY_OF_WEEK 6, PLAYER_HEARTS Current Harvey 8, !PLAYER_HAS_MAIL Current mailHarveyNoteGirlfriend Received",
                //   "Actions": [
                //     "AddMail Current mailHarveyNoteGirlfriend now"
                //   ],
                //   "LogName": "Load Triggers/Harvey Note Girlfriend #1"
                // },
            }
        }
    ]
}